INSTALL
MANIFEST.in
README.rst
setup.py
isonasacs/__init__.py
isonasacs/test.py
isonasacs.egg-info/PKG-INFO
isonasacs.egg-info/SOURCES.txt
isonasacs.egg-info/dependency_links.txt
isonasacs.egg-info/pbr.json
isonasacs.egg-info/top_level.txt