Metadata-Version: 1.1
Name: isonasacs
Version: 0.5
Summary: A module to manage ISONAS Access Control System
Home-page: https://github.com/LavaLab/isonasacs
Author: Lava Lab Software
Author-email: mail@lavalab.com.au
License: BSD
Platform: UNKNOWN
Classifier: Intended Audience :: Developers
Classifier: License :: OSI Approved :: BSD License
Classifier: Operating System :: OS Independent
Classifier: Programming Language :: Python :: 2
Classifier: Programming Language :: Python :: 2.7
Classifier: Programming Language :: Python :: 3
Classifier: Topic :: Office/Business
Classifier: Topic :: Software Development :: Libraries
Classifier: Topic :: Utilities
